py3tools
