Metadata-Version: 1.1
Name: py3tools
Version: 0.0.6
Summary: Python3 tools
Home-page: https://github.com/chaluemwut/pytools.git
Author: Chaluemwut Noyunsan
Author-email: UNKNOWN
License: UNKNOWN
Download-URL: https://github.com/chaluemwut/pytools.git
Platform: UNKNOWN
